{
  "createdAt": 1666260827481,
  "updatedAt": 1666260827481,
  "deletedAt": 0,
  "createdFirstAt": 1666260827481,
  "id": "namedparameterstypeof-askok",
  "name": "NamedParameters<typeof askOk>",
  "slug": "namedparameterstypeof-askok",
  "operationRelativeTypescriptFilePath": "src/general.ts",
  "hasGeneric": false,
  "isExported": false,
  "isOperationIndex": false,
  "description": "",
  "isDbModel": false,
  "commentsInside": [],
  "type": {
    "typeDefinition": {
      "type": "object",
      "properties": {
        "question": {
          "type": "string"
        }
      },
      "required": [
        "question"
      ],
      "additionalProperties": false
    },
    "simplifiedSchema": {
      "properties": [
        {
          "name": "question",
          "required": true,
          "schema": {
            "type": "string"
          }
        }
      ],
      "type": "object"
    },
    "typeCoverage": 0,
    "rawType": "NamedParameters<typeof askOk>",
    "isArray": false,
    "isEnum": false,
    "isEnumLiteral": false,
    "isObject": false,
    "isPrimitive": false
  }
}