{
  "createdAt": 1663470829909,
  "updatedAt": 1663470829909,
  "deletedAt": 0,
  "createdFirstAt": 1663470829909,
  "id": "markdown",
  "name": "Markdown",
  "slug": "markdown",
  "operationRelativeTypescriptFilePath": "src/common.ts",
  "hasGeneric": false,
  "isExported": true,
  "rawText": "\n\n/**\n * a string that is known to contain markdown.\n */\nexport type Markdown = string;",
  "extensions": [],
  "isOperationIndex": false,
  "description": "a string that is known to contain markdown.",
  "isDbModel": false,
  "commentsInside": [],
  "type": {
    "typeDefinition": {
      "type": "string",
      "description": "a string that is known to contain markdown."
    },
    "simplifiedSchema": {
      "description": "a string that is known to contain markdown.",
      "type": "string"
    },
    "typeCoverage": 0,
    "rawType": "Markdown",
    "isArray": false,
    "isEnum": false,
    "isEnumLiteral": false,
    "isObject": false,
    "isPrimitive": false
  }
}