[
  {
    "createdAt": 1666260307878,
    "updatedAt": 1666260307878,
    "deletedAt": 0,
    "createdFirstAt": 1666260307878,
    "name": "TsInterface",
    "slug": "ts-interface",
    "type": "type",
    "hasGeneric": false,
    "module": "code-types",
    "isModuleResolved": true,
    "comments": [],
    "operationRelativeTypescriptFilePath": "src/dbUtil.ts",
    "classification": "operation",
    "isAbsolute": true,
    "isModuleFromMonorepo": true,
    "id": "nwayjqgcwbquuptmvygjnvyi"
  },
  {
    "createdAt": 1666260307878,
    "updatedAt": 1666260307878,
    "deletedAt": 0,
    "createdFirstAt": 1666260307878,
    "name": "db",
    "slug": "db",
    "type": "value",
    "module": "database",
    "isModuleResolved": true,
    "comments": [],
    "operationRelativeTypescriptFilePath": "src/dbUtil.ts",
    "classification": "operation",
    "isAbsolute": true,
    "isModuleFromMonorepo": true,
    "id": "skmtcewivxzwiquijgljsbad"
  },
  {
    "createdAt": 1666260307878,
    "updatedAt": 1666260307878,
    "deletedAt": 0,
    "createdFirstAt": 1666260307878,
    "name": "onlyUnique2",
    "slug": "only-unique-2",
    "type": "value",
    "module": "js-util",
    "isModuleResolved": true,
    "comments": [],
    "operationRelativeTypescriptFilePath": "src/dbUtil.ts",
    "classification": "operation",
    "isAbsolute": true,
    "isModuleFromMonorepo": true,
    "id": "olmikfurqcleywfostptxzjr"
  }
]