[
  {
    "createdAt": 1671365953525,
    "updatedAt": 1671365953525,
    "deletedAt": 0,
    "createdFirstAt": 1671365953525,
    "name": "DefaultModelType",
    "slug": "default-model-type",
    "type": "type",
    "hasGeneric": false,
    "module": "model-types",
    "isModuleResolved": true,
    "comments": [],
    "operationRelativeTypescriptFilePath": "src/AiDemoApp.ts",
    "classification": "operation",
    "isAbsolute": true,
    "isModuleFromMonorepo": true,
    "id": "ekxbdyjmztakqqbjfhjqyhvr"
  },
  {
    "createdAt": 1671365953526,
    "updatedAt": 1671365953526,
    "deletedAt": 0,
    "createdFirstAt": 1671365953526,
    "name": "SlugModelType",
    "slug": "slug-model-type",
    "type": "type",
    "hasGeneric": false,
    "module": "model-types",
    "isModuleResolved": true,
    "comments": [],
    "operationRelativeTypescriptFilePath": "src/AiDemoApp.ts",
    "classification": "operation",
    "isAbsolute": true,
    "isModuleFromMonorepo": true,
    "id": "xserbaifckyyziqsdwnscykf"
  },
  {
    "createdAt": 1671365953526,
    "updatedAt": 1671365953526,
    "deletedAt": 0,
    "createdFirstAt": 1671365953526,
    "name": "SlugModelType",
    "slug": "slug-model-type",
    "type": "type",
    "hasGeneric": false,
    "module": "model-types",
    "isModuleResolved": true,
    "comments": [],
    "operationRelativeTypescriptFilePath": "src/ContextualPrompt.ts",
    "classification": "operation",
    "isAbsolute": true,
    "isModuleFromMonorepo": true,
    "id": "wjeubmzpmundsdptkwpieqpl"
  },
  {
    "createdAt": 1671365953526,
    "updatedAt": 1671365953526,
    "deletedAt": 0,
    "createdFirstAt": 1671365953526,
    "name": "FileType",
    "slug": "file-type",
    "type": "type",
    "hasGeneric": false,
    "module": "filename-conventions",
    "isModuleResolved": true,
    "comments": [],
    "operationRelativeTypescriptFilePath": "src/ContextualPrompt.ts",
    "classification": "operation",
    "isAbsolute": true,
    "isModuleFromMonorepo": true,
    "id": "qtqgmvruhmcrfgtjaeawjgal"
  },
  {
    "createdAt": 1671365953526,
    "updatedAt": 1671365953526,
    "deletedAt": 0,
    "createdFirstAt": 1671365953526,
    "name": "ContextualPrompt",
    "slug": "contextual-prompt",
    "module": "./ContextualPrompt",
    "isModuleResolved": true,
    "comments": [],
    "operationRelativeTypescriptFilePath": "src/ContextualPromptObject.ts",
    "classification": "internal",
    "isAbsolute": false,
    "isModuleFromMonorepo": false,
    "id": "vhgsmefkmksikjcnvrzhmmmv"
  },
  {
    "createdAt": 1671365953526,
    "updatedAt": 1671365953526,
    "deletedAt": 0,
    "createdFirstAt": 1671365953526,
    "name": "DefaultModelType",
    "slug": "default-model-type",
    "type": "type",
    "hasGeneric": false,
    "module": "model-types",
    "isModuleResolved": true,
    "comments": [],
    "operationRelativeTypescriptFilePath": "src/ContextualPromptResult.ts",
    "classification": "operation",
    "isAbsolute": true,
    "isModuleFromMonorepo": true,
    "id": "mpmqosxdyuyjnroeldouulyt"
  },
  {
    "createdAt": 1671365953526,
    "updatedAt": 1671365953526,
    "deletedAt": 0,
    "createdFirstAt": 1671365953526,
    "name": "BackendAsset",
    "slug": "backend-asset",
    "type": "type",
    "hasGeneric": false,
    "module": "asset-type",
    "isModuleResolved": true,
    "comments": [],
    "operationRelativeTypescriptFilePath": "src/ContextualPromptResult.ts",
    "classification": "operation",
    "isAbsolute": true,
    "isModuleFromMonorepo": true,
    "id": "whigwhxigmolawxtmwxibvbv"
  },
  {
    "createdAt": 1671365953527,
    "updatedAt": 1671365953527,
    "deletedAt": 0,
    "createdFirstAt": 1671365953527,
    "name": "DefaultModelType",
    "slug": "default-model-type",
    "type": "type",
    "hasGeneric": false,
    "module": "model-types",
    "isModuleResolved": true,
    "comments": [],
    "operationRelativeTypescriptFilePath": "src/GptIdeasUser.ts",
    "classification": "operation",
    "isAbsolute": true,
    "isModuleFromMonorepo": true,
    "id": "euuxrpcxloahvbwxuoawtiuc"
  },
  {
    "createdAt": 1671365953527,
    "updatedAt": 1671365953527,
    "deletedAt": 0,
    "createdFirstAt": 1671365953527,
    "name": "BackendAsset",
    "slug": "backend-asset",
    "type": "type",
    "hasGeneric": false,
    "module": "asset-type",
    "isModuleResolved": true,
    "comments": [],
    "operationRelativeTypescriptFilePath": "src/ProcessPromptFunctionResult.ts",
    "classification": "operation",
    "isAbsolute": true,
    "isModuleFromMonorepo": true,
    "id": "sxlvagtkhfbphyhzysndzrjj"
  },
  {
    "createdAt": 1671365953527,
    "updatedAt": 1671365953527,
    "deletedAt": 0,
    "createdFirstAt": 1671365953527,
    "name": "ContextualPromptInfo",
    "slug": "contextual-prompt-info",
    "module": "./ContextualPrompt",
    "isModuleResolved": true,
    "comments": [],
    "operationRelativeTypescriptFilePath": "src/PromptFunction.ts",
    "classification": "internal",
    "isAbsolute": false,
    "isModuleFromMonorepo": false,
    "id": "pkeghtalnbwszpkgpysvnlpn"
  },
  {
    "createdAt": 1671365953527,
    "updatedAt": 1671365953527,
    "deletedAt": 0,
    "createdFirstAt": 1671365953527,
    "name": "ProcessPromptFunctionResult",
    "slug": "process-prompt-function-result",
    "module": "./ProcessPromptFunctionResult",
    "isModuleResolved": true,
    "comments": [],
    "operationRelativeTypescriptFilePath": "src/PromptFunction.ts",
    "classification": "internal",
    "isAbsolute": false,
    "isModuleFromMonorepo": false,
    "id": "tygdhwwfqevszeyymamtxnep"
  },
  {
    "createdAt": 1671365953527,
    "updatedAt": 1671365953527,
    "deletedAt": 0,
    "createdFirstAt": 1671365953527,
    "name": "Frontmatter",
    "slug": "frontmatter",
    "type": "type",
    "hasGeneric": false,
    "module": "matter-types",
    "isModuleResolved": true,
    "comments": [],
    "operationRelativeTypescriptFilePath": "src/ReaderProps.ts",
    "classification": "operation",
    "isAbsolute": true,
    "isModuleFromMonorepo": true,
    "id": "urszeajxpgpsgxvxypwjhqpz"
  },
  {
    "createdAt": 1671365953527,
    "updatedAt": 1671365953527,
    "deletedAt": 0,
    "createdFirstAt": 1671365953527,
    "name": "ContextualPromptsObject",
    "slug": "contextual-prompts-object",
    "module": "./ContextualPromptObject",
    "isModuleResolved": true,
    "comments": [],
    "operationRelativeTypescriptFilePath": "src/ReaderProps.ts",
    "classification": "internal",
    "isAbsolute": false,
    "isModuleFromMonorepo": false,
    "id": "hwptgttjxhjyytdxeepkoove"
  },
  {
    "createdAt": 1671365953527,
    "updatedAt": 1671365953527,
    "deletedAt": 0,
    "createdFirstAt": 1671365953527,
    "name": "ContextualPromptResult",
    "slug": "contextual-prompt-result",
    "module": "./ContextualPromptResult",
    "isModuleResolved": true,
    "comments": [],
    "operationRelativeTypescriptFilePath": "src/ReaderProps.ts",
    "classification": "internal",
    "isAbsolute": false,
    "isModuleFromMonorepo": false,
    "id": "jriyoigrnwgavilyoilkgslw"
  }
]