[
  {
    "createdAt": 1674135459865,
    "updatedAt": 1674135459865,
    "deletedAt": 0,
    "createdFirstAt": 1674135459865,
    "name": "docsGetPages",
    "slug": "docs-get-pages",
    "operationRelativeTypescriptFilePath": "src/docsGetPages.ts",
    "comments": [],
    "type": "value",
    "id": "rdmxvyqplruktotldypaprpu"
  },
  {
    "createdAt": 1674135459865,
    "updatedAt": 1674135459865,
    "deletedAt": 0,
    "createdFirstAt": 1674135459865,
    "name": "getMarkdownReaderPages",
    "slug": "get-markdown-reader-pages",
    "operationRelativeTypescriptFilePath": "src/getMarkdownReaderPages.ts",
    "comments": [],
    "type": "value",
    "id": "nurpcjfkotiizhbwvpspnwbv"
  },
  {
    "createdAt": 1674135459865,
    "updatedAt": 1674135459865,
    "deletedAt": 0,
    "createdFirstAt": 1674135459865,
    "name": "getPublicMarkdownFilePaths",
    "slug": "get-public-markdown-file-paths",
    "operationRelativeTypescriptFilePath": "src/getPublicMarkdownFilePaths.ts",
    "comments": [],
    "type": "value",
    "id": "certlnmacqwckzveqtjfafuh"
  },
  {
    "createdAt": 1674135459865,
    "updatedAt": 1674135459865,
    "deletedAt": 0,
    "createdFirstAt": 1674135459865,
    "name": "availableExtensions",
    "slug": "available-extensions",
    "operationRelativeTypescriptFilePath": "src/removeExtensionsFromPath.ts",
    "comments": [],
    "type": "value",
    "id": "prhqmiqcmycpujtdbetddgog"
  },
  {
    "createdAt": 1674135459866,
    "updatedAt": 1674135459866,
    "deletedAt": 0,
    "createdFirstAt": 1674135459866,
    "name": "removeExtensionsFromPath",
    "slug": "remove-extensions-from-path",
    "operationRelativeTypescriptFilePath": "src/removeExtensionsFromPath.ts",
    "comments": [],
    "type": "value",
    "id": "dugbkhjnazzpnanpacrzzree"
  },
  {
    "createdAt": 1674135459866,
    "updatedAt": 1674135459866,
    "deletedAt": 0,
    "createdFirstAt": 1674135459866,
    "name": "removeNumberPrefix",
    "slug": "remove-number-prefix",
    "operationRelativeTypescriptFilePath": "src/removeNumberPrefix.ts",
    "comments": [],
    "type": "value",
    "id": "bornimwmmzhxxgtgsfneclrt"
  },
  {
    "createdAt": 1674135459866,
    "updatedAt": 1674135459866,
    "deletedAt": 0,
    "createdFirstAt": 1674135459866,
    "name": "shouldExposeMarkdownFile",
    "slug": "should-expose-markdown-file",
    "operationRelativeTypescriptFilePath": "src/shouldExposeMarkdownFile.ts",
    "comments": [],
    "type": "value",
    "id": "rgdlnmajoofdcjdldxkofind"
  },
  {
    "createdAt": 1674135459866,
    "updatedAt": 1674135459866,
    "deletedAt": 0,
    "createdFirstAt": 1674135459866,
    "name": "stripReadmeFromFolder",
    "slug": "strip-readme-from-folder",
    "operationRelativeTypescriptFilePath": "src/stripReadmeFromFolder.ts",
    "comments": [],
    "type": "value",
    "id": "znbxjifzftpywcvgbruobwin"
  }
]