{
  "createdAt": 1662719061247,
  "updatedAt": 1662888553343,
  "deletedAt": 0,
  "createdFirstAt": 1662719061247,
  "folderName": "watch-operations",
  "packageName": "watch-operations",
  "relativeOperationLocationPath": "operations/tools/control-fs",
  "classification": "node",
  "name": "watch-operations",
  "slug": "watch-operations",
  "coreDependencies": [],
  "operationDependencies": [
    "getAllOperationSourcePaths",
    "log",
    "getProjectRoot",
    "watchFoldersFs",
    "getAllOperationSourcePaths",
    "log",
    "rebuildOperation",
    "getProjectRoot"
  ],
  "packageDependencies": [
    "execSync"
  ],
  "size": {
    "codeSize": {
      "numberOfFiles": 3,
      "lines": 155,
      "characters": 3909,
      "bytes": 3913
    },
    "dataSize": {
      "numberOfFiles": 2,
      "lines": 71,
      "characters": 1524,
      "bytes": 1524
    },
    "textSize": {
      "numberOfFiles": 2,
      "lines": 113,
      "characters": 1703,
      "bytes": 1703
    },
    "size": {
      "bytes": 7140,
      "characters": 7136,
      "lines": 339,
      "numberOfFiles": 7
    }
  },
  "buildSucceeded": true,
  "dependenciesBuildsFailed": false,
  "indexErrors": [],
  "indexImportExportError": "",
  "indexInteracesErrors": "[\"No schema/definitions found for /Users/king/King/operations/tools/control-fs/watch-operations/src/watchOperations.ts. Error: Error: Expression expected.\"]",
  "lintProblems": [],
  "id": "iOhpqlbmPyfeYGNR",
  "language": "en"
}